[
        {
            
            "FolioGEPP":"36755",
            "FechaGeneracion":"2022-01-11T18:58:24",
            "UsoCFDI": "03-Gastos","DocumentosGEPP":{"DocsGEPP":["R5400000478M"]}},{"CartaPorte":{
            "Version":"2.0",
            "TranspInternac":"No",
            "TotalDistRec":5,"Ubicaciones":{
            "Ubicacion":[
        {
            "TipoUbicacion":"Origen",
            "IDUbicacion":"OR408003"
            
            ,"RFCRemitenteDestinatario":"BPU7901018D4"
            ,"FechaHoraSalidaLlegada":"2022-01-11T19:08:24"
            ,"Domicilio":{
            "Estado":"OAX","Pais":"MEX","CodigoPostal":"68039"}
        },{
            "TipoUbicacion":"Destino",
            "IDUbicacion":"DE407102"
            
            ,"RFCRemitenteDestinatario":"XAXX010101000","FechaHoraSalidaLlegada":"2022-01-11T19:38:24"
            ,"DistanciaRecorrida": 5
            ,"Domicilio":{
            "Estado":"OAX","Pais":"MEX","CodigoPostal":"68090"}
        }
            ]
        },"Mercancias":{
            "PesoBrutoTotal": "1560.08",
            "UnidadPeso": "KGM",
            "PesoNetoTotal": "1560.08",
            "NumTotalMercancias":4,
            "Mercancia":[{
            "BienesTransp":"50202306",
            "Descripcion":"Refrescos",
            "Cantidad":"77",
            "ClaveUnidad":"XBX",
            "Unidad":"Caja",
            "PesoEnKg":"1330.36"
            
            
            
        },{
            "BienesTransp":"50202300",
            "Descripcion":"Bebidas no alcohólicas",
            "Cantidad":"1",
            "ClaveUnidad":"XBX",
            "Unidad":"Caja",
            "PesoEnKg":"5.1"
            
            
            
        },{
            "BienesTransp":"50202309",
            "Descripcion":"Bebidas deportivas o de energía",
            "Cantidad":"18",
            "ClaveUnidad":"XBX",
            "Unidad":"Caja",
            "PesoEnKg":"76.82"
            
            
            
        },{
            "BienesTransp":"50202301",
            "Descripcion":"Agua",
            "Cantidad":"20",
            "ClaveUnidad":"XBX",
            "Unidad":"Caja",
            "PesoEnKg":"147.8"
            
            
            
        }]}
            }
        }]